timescope-0.1.1.dist-info/METADATA
timescope-0.1.1.dist-info/WHEEL
timescope-0.1.1.dist-info/license_files/LICENSE
timescope/__init__.py
timescope/__init__.pyi
timescope/py.typed
timescope/timescope.pypy39-pp73-x86_64-linux-gnu.so
timescope-0.1.1.dist-info/RECORD
