Metadata-Version: 2.1
Name: timescope
Version: 0.1.1
Classifier: Programming Language :: Rust
Classifier: Programming Language :: Python :: Implementation :: CPython
Classifier: Programming Language :: Python :: Implementation :: PyPy
Classifier: Programming Language :: Python :: 3.7
Classifier: Programming Language :: Python :: 3.8
Classifier: Programming Language :: Python :: 3.9
Classifier: Programming Language :: Python :: 3.10
Classifier: Programming Language :: Python :: 3.11
License-File: LICENSE
Summary: Simple Python library written in Rust for analyzing and scoping out patterns in time series data
Home-Page: https://github.com/evertoncolling/timescope
Author: Everton Colling <evertoncolling@gmail.com>
Author-email: Everton Colling <evertoncolling@gmail.com>
License: MIT
Requires-Python: >=3.7
Project-URL: repository, https://github.com/evertoncolling/timescope
Project-URL: homepage, https://github.com/evertoncolling/timescope
Project-URL: documentation, https://github.com/evertoncolling/timescope
